qgel/__init__.py
qgel/qgel.py
qgel-0.1.3.dist-info/METADATA
qgel-0.1.3.dist-info/WHEEL
qgel-0.1.3.dist-info/top_level.txt
qgel-0.1.3.dist-info/RECORD
