Metadata-Version: 2.1
Name: qgel
Version: 0.1.3
Summary: A quick way to qgel
Home-page: http://github.com/egolinko/qgel
Author: Eric Golinko
Author-email: egolinko@gmail.com
License: MIT
